{
	"info": {
		"_postman_id": "704ad426-69cf-4778-8078-bb6ccc528930",
		"name": "tasks-api",
		"schema": "https://schema.getpostman.com/json/collection/v2.1.0/collection.json",
		"_exporter_id": "18573665"
	},
	"item": [
		{
			"name": "Get all tasks",
			"request": {
				"method": "GET",
				"header": [],
				"url": {
					"raw": "localhost:8080/api/tasks",
					"host": [
						"localhost"
					],
					"port": "8080",
					"path": [
						"api",
						"tasks"
					]
				}
			},
			"response": []
		},
		{
			"name": "create task",
			"request": {
				"method": "POST",
				"header": [],
				"body": {
					"mode": "raw",
					"raw": "{\r\n    \"title\": \"Crear aplicacion usando arquitectura hexagonal\",\r\n    \"description\": \"Aplicacion de listas de tareas\",\r\n    \"completed\": true\r\n}",
					"options": {
						"raw": {
							"language": "json"
						}
					}
				},
				"url": {
					"raw": "localhost:8080/api/tasks/create",
					"host": [
						"localhost"
					],
					"port": "8080",
					"path": [
						"api",
						"tasks",
						"create"
					]
				}
			},
			"response": []
		}
	]
}